print_matrix.py
print_matrix-0.1.0.dist-info/METADATA
print_matrix-0.1.0.dist-info/WHEEL
print_matrix-0.1.0.dist-info/RECORD
