Metadata-Version: 2.1
Name: print-matrix
Version: 0.1.0
Summary: Prints a list of strings in a matrix for easy viewing
Author: Caleb Crouse
Requires-Python: >=3.9,<4.0
Classifier: Programming Language :: Python :: 3
Classifier: Programming Language :: Python :: 3.9
Classifier: Programming Language :: Python :: 3.10
Classifier: Programming Language :: Python :: 3.11
Classifier: Programming Language :: Python :: 3.12
